nix_playground/__init__.py
nix_playground/build.py
nix_playground/checkout.py
nix_playground/clean.py
nix_playground/cli.py
nix_playground/constants.py
nix_playground/environment.py
nix_playground/main.py
nix_playground/patch.py
nix_playground/utils.py
nix_playground-1.0.3.dist-info/METADATA
nix_playground-1.0.3.dist-info/WHEEL
nix_playground-1.0.3.dist-info/entry_points.txt
nix_playground-1.0.3.dist-info/licenses/LICENSE
nix_playground-1.0.3.dist-info/RECORD
