Metadata-Version: 2.4
Name: nix-playground
Version: 1.0.3
Summary: Tool for patching nixpkgs package source code easily
License-File: LICENSE
Requires-Python: >=3.11
Requires-Dist: click>=8.1.7
Requires-Dist: pygit2>=1.17.0
Requires-Dist: rich>=13.9.4
